{
  "resolvedId": "C:/Users/Andrew/Documents/GitHub/jtoh-xl-tower-tracker/components/Loading.vue",
  "transforms": [
    {
      "name": "vite:load-fallback",
      "result": "<template>\r\n  <div\r\n    v-if=\"modelValue\"\r\n    class=\"border-gray-300 h-10 w-10 animate-spin rounded-full border-4 border-t-blue-600\"\r\n  />\r\n</template>\r\n<script lang=\"ts\">\r\nexport default {\r\n  name: \"Loading\",\r\n  props: [\"modelValue\"],\r\n  emits: [\"update:modelValue\"],\r\n};\r\n</script>\r\n",
      "start": 1705353510373,
      "end": 1705353510627,
      "sourcemaps": null
    },
    {
      "name": "nuxt:layer-aliasing",
      "start": 1705353510627,
      "end": 1705353510627,
      "order": "pre"
    },
    {
      "name": "nuxt:server-devonly:transform",
      "start": 1705353510627,
      "end": 1705353510627,
      "order": "pre"
    },
    {
      "name": "nuxt:client-fallback-auto-id",
      "start": 1705353510627,
      "end": 1705353510627,
      "order": "pre"
    },
    {
      "name": "vite:css",
      "start": 1705353510627,
      "end": 1705353510627,
      "order": "normal"
    },
    {
      "name": "vite:esbuild",
      "start": 1705353510627,
      "end": 1705353510627,
      "order": "normal"
    },
    {
      "name": "vite:json",
      "start": 1705353510627,
      "end": 1705353510627,
      "order": "normal"
    },
    {
      "name": "vite:worker",
      "start": 1705353510627,
      "end": 1705353510627,
      "order": "normal"
    },
    {
      "name": "vite:vue",
      "result": "import _sfc_main from \"C:/Users/Andrew/Documents/GitHub/jtoh-xl-tower-tracker/components/Loading.vue?vue&type=script&lang.ts\";\nexport * from \"C:/Users/Andrew/Documents/GitHub/jtoh-xl-tower-tracker/components/Loading.vue?vue&type=script&lang.ts\";\nimport { openBlock as _openBlock, createElementBlock as _createElementBlock, createCommentVNode as _createCommentVNode } from \"vue\";\nconst _hoisted_1 = {\n  key: 0,\n  class: \"border-gray-300 h-10 w-10 animate-spin rounded-full border-4 border-t-blue-600\"\n};\nfunction _sfc_render(_ctx, _cache, $props, $setup, $data, $options) {\n  return $props.modelValue ? (_openBlock(), _createElementBlock(\"div\", _hoisted_1)) : _createCommentVNode(\"\", true);\n}\nimport _export_sfc from \"\\0plugin-vue:export-helper\";\nexport default /* @__PURE__ */ _export_sfc(_sfc_main, [[\"render\", _sfc_render]]);\n",
      "start": 1705353510627,
      "end": 1705353510914,
      "order": "normal",
      "sourcemaps": {
        "mappings": ""
      }
    },
    {
      "name": "vite:vue-jsx",
      "start": 1705353510914,
      "end": 1705353510914,
      "order": "normal"
    },
    {
      "name": "replace",
      "start": 1705353510914,
      "end": 1705353510914,
      "order": "normal"
    },
    {
      "name": "nuxt:remove-plugin-metadata",
      "start": 1705353510914,
      "end": 1705353510914,
      "order": "normal"
    },
    {
      "name": "nuxt:chunk-error",
      "start": 1705353510914,
      "end": 1705353510914,
      "order": "normal"
    },
    {
      "name": "nuxt:components:imports",
      "start": 1705353510914,
      "end": 1705353510914,
      "order": "normal"
    },
    {
      "name": "replace",
      "start": 1705353510914,
      "end": 1705353510914,
      "order": "normal"
    },
    {
      "name": "ssr-styles",
      "start": 1705353510914,
      "end": 1705353510914,
      "order": "normal"
    },
    {
      "name": "vite:define",
      "start": 1705353510914,
      "end": 1705353510914,
      "order": "normal"
    },
    {
      "name": "vite:css-post",
      "start": 1705353510915,
      "end": 1705353510915,
      "order": "normal"
    },
    {
      "name": "vite:build-html",
      "start": 1705353510915,
      "end": 1705353510915,
      "order": "normal"
    },
    {
      "name": "vite:worker-import-meta-url",
      "start": 1705353510915,
      "end": 1705353510915,
      "order": "normal"
    },
    {
      "name": "vite:asset-import-meta-url",
      "start": 1705353510915,
      "end": 1705353510915,
      "order": "normal"
    },
    {
      "name": "commonjs",
      "start": 1705353510915,
      "end": 1705353510915,
      "order": "normal"
    },
    {
      "name": "vite:dynamic-import-vars",
      "start": 1705353510915,
      "end": 1705353510915,
      "order": "normal"
    },
    {
      "name": "vite:import-glob",
      "start": 1705353510915,
      "end": 1705353510915,
      "order": "normal"
    },
    {
      "name": "nuxt:composable-keys",
      "start": 1705353510915,
      "end": 1705353510915,
      "order": "post"
    },
    {
      "name": "nuxt:imports-transform",
      "start": 1705353510915,
      "end": 1705353510917,
      "order": "post"
    },
    {
      "name": "unctx:transform",
      "start": 1705353510917,
      "end": 1705353510917,
      "order": "post"
    },
    {
      "name": "nuxt:pages-macros-transform",
      "start": 1705353510924,
      "end": 1705353510924,
      "order": "post"
    },
    {
      "name": "nuxt:runtime-paths-dep",
      "start": 1705353510928,
      "end": 1705353510928,
      "order": "post"
    },
    {
      "name": "nuxt:route-injection-plugin",
      "start": 1705353510928,
      "end": 1705353510928,
      "order": "post"
    },
    {
      "name": "nuxt:components-loader",
      "start": 1705353510928,
      "end": 1705353510928,
      "order": "post"
    },
    {
      "name": "nuxt:tree-shake-composables:transform",
      "start": 1705353510929,
      "end": 1705353510929,
      "order": "post"
    },
    {
      "name": "vite:build-import-analysis",
      "start": 1705353510929,
      "end": 1705353510929,
      "order": "normal"
    },
    {
      "name": "vite:reporter",
      "start": 1705353510929,
      "end": 1705353510929,
      "order": "normal"
    }
  ]
}
